<title>Keladon</title>
<author>Laura Holmegaard</author>
<timestamp>2009-10-28T16:49:01Z</timestamp>
<text>&apos;&apos;&apos;Keladon&apos;&apos;&apos; er en adelig [[højelver]]familie, som er berømt for at være den slægt, der har haft flest [[højkonge|højkonger]] og [[højdronning|højdronninger]] på tronen. Den nuværende regent af [[Eislonien]] er [[Aencar Keladon]], som er opkaldt efter den første højkonge over [[elver|elverne]] nogensinde.

Nogle siger, at Aencar Keladon har ødelagt sin families chancer for nogensinde igen at få en regent på tronen, da han giftede sig med [[skovelver|skovelveren]] [[Anarzee Løvdanser]], idet ingen skovelver før hende nogensinde har siddet på tronen.</text>
<copyright>Keladon</copyright>
