<title>Skyggesjakalens stamme</title>
<author>Laura Holmegaard</author>
<timestamp>2010-06-16T10:35:13Z</timestamp>
<text>&apos;&apos;&apos;Skyggesjakalens stamme&apos;&apos;&apos; er en af de største stammer på [[Traegonn Sletten]] og har en plads i [[Himmelbjergets højråd]].

Stammens medlemmer er udprægede tilbedere af [[Skygge|Skyggerne]] og kendt for sin tætte kontakt til disse væsener, hvilket blandt andet kommer til udtryk i deres brug af [[Skyggeulv|Skyggeulve]]. På grund af denne stærke forbindelse til Skyggerne, der er kendt for at være ildesindede og farlige selv for de, som kender dem indgående og tjener dem trofast, er Skyggesjakalens stamme frygtet selv blandt andre [[traegonner|traegonnere]], men også højt respekteret. Nogle af [[Niraham|Nirahams]] stærkeste [[heks|hekse]] stammer fra denne klan.

Skyggesjakalens stamme holder til i de nordlige dele af Traegonn langs grænsen til [[Rustbjergene]].</text>
<copyright>Skyggesjakalens stamme</copyright>
